pyqif/__init__.py
pyqif/hyper_calc.py
pyqif/latex_converter.py
pyqif-0.0.5.dist-info/LICENSE
pyqif-0.0.5.dist-info/METADATA
pyqif-0.0.5.dist-info/WHEEL
pyqif-0.0.5.dist-info/entry_points.txt
pyqif-0.0.5.dist-info/top_level.txt
pyqif-0.0.5.dist-info/RECORD
