Metadata-Version: 2.1
Name: pyqif
Version: 0.0.5
Summary: A tool for calculating the hyper distribution from pushing a prior into a channel. Quantitative Information Flow.
Home-page: https://github.com/LucasStarlingdePaulaSalles/hyper-distributor
Author: Lucas Starling
Author-email: lucastarling1@gmail.com
License: UNKNOWN
Platform: UNKNOWN
Classifier: Programming Language :: Python :: 3
Classifier: License :: OSI Approved :: MIT License
Classifier: Operating System :: OS Independent
Requires: numpy
License-File: LICENSE
Requires-Dist: numpy
